README.md
setup.py
shellify/__init__.py
shellify/bin.py
shellify/shell_factory.py
shellify.egg-info/PKG-INFO
shellify.egg-info/SOURCES.txt
shellify.egg-info/dependency_links.txt
shellify.egg-info/not-zip-safe
shellify.egg-info/top_level.txt