Metadata-Version: 1.1
Name: shellify
Version: 0.4.1
Summary: Turn any python module into a shell!
Home-page: https://bitbucket.org/johannestaas/shellify
Author: Johan Nestaas
Author-email: johannestaas@gmail.com
License: GPLv3+
Keywords: shell python command line cli terminal
Platform: UNKNOWN
Classifier: Development Status :: 4 - Beta
Classifier: License :: OSI Approved :: GNU General Public License v3 or later (GPLv3+)
Classifier: Environment :: Console
Classifier: Environment :: X11 Applications :: Qt
Classifier: Environment :: MacOS X
Classifier: Environment :: Win32 (MS Windows)
Classifier: Operating System :: POSIX
Classifier: Operating System :: MacOS :: MacOS X
Classifier: Operating System :: Microsoft :: Windows
Classifier: Programming Language :: Python
